odoo/addons/attachment_synchronize/README.rst
odoo/addons/attachment_synchronize/__init__.py
odoo/addons/attachment_synchronize/__manifest__.py
odoo/addons/attachment_synchronize/data/cron.xml
odoo/addons/attachment_synchronize/demo/attachment_synchronize_task_demo.xml
odoo/addons/attachment_synchronize/i18n/attachment_synchronize.pot
odoo/addons/attachment_synchronize/i18n/es.po
odoo/addons/attachment_synchronize/i18n/it.po
odoo/addons/attachment_synchronize/migrations/18.0.1.0.0/pre-migrate.py
odoo/addons/attachment_synchronize/models/__init__.py
odoo/addons/attachment_synchronize/models/attachment_queue.py
odoo/addons/attachment_synchronize/models/attachment_synchronize_task.py
odoo/addons/attachment_synchronize/models/storage_backend.py
odoo/addons/attachment_synchronize/readme/CONTRIBUTORS.md
odoo/addons/attachment_synchronize/readme/DESCRIPTION.md
odoo/addons/attachment_synchronize/readme/USAGE.md
odoo/addons/attachment_synchronize/security/ir.model.access.csv
odoo/addons/attachment_synchronize/static/description/export_task.png
odoo/addons/attachment_synchronize/static/description/icon.png
odoo/addons/attachment_synchronize/static/description/import_task.png
odoo/addons/attachment_synchronize/static/description/index.html
odoo/addons/attachment_synchronize/tests/__init__.py
odoo/addons/attachment_synchronize/tests/common.py
odoo/addons/attachment_synchronize/tests/test_export.py
odoo/addons/attachment_synchronize/tests/test_import.py
odoo/addons/attachment_synchronize/views/attachment_queue_views.xml
odoo/addons/attachment_synchronize/views/attachment_synchronize_task_views.xml
odoo/addons/attachment_synchronize/views/storage_backend_views.xml
odoo_addon_attachment_synchronize-18.0.1.0.0.2.dist-info/METADATA
odoo_addon_attachment_synchronize-18.0.1.0.0.2.dist-info/WHEEL
odoo_addon_attachment_synchronize-18.0.1.0.0.2.dist-info/top_level.txt
odoo_addon_attachment_synchronize-18.0.1.0.0.2.dist-info/RECORD
