Metadata-Version: 2.1
Name: odoo-addon-attachment_synchronize
Version: 18.0.1.0.0.2
Requires-Python: >=3.10
Requires-Dist: odoo-addon-attachment_queue==18.0.*
Requires-Dist: odoo-addon-fs_storage==18.0.*
Requires-Dist: odoo==18.0.*
Summary: Attachment Synchronize
Home-page: https://github.com/OCA/server-tools
License: AGPL-3
Author: Akretion,Odoo Community Association (OCA)
Author-email: support@odoo-community.org
Classifier: Programming Language :: Python
Classifier: Framework :: Odoo
Classifier: Framework :: Odoo :: 18.0
Classifier: License :: OSI Approved :: GNU Affero General Public License v3
Classifier: Development Status :: 4 - Beta
